nonebot_plugin_qwen_chat/__init__.py
nonebot_plugin_qwen_chat/config.py
nonebot_plugin_qwen_chat/message_handler.py
nonebot_plugin_qwen_chat-0.1.0b1.dist-info/licenses/LICENSE
nonebot_plugin_qwen_chat-0.1.0b1.dist-info/METADATA
nonebot_plugin_qwen_chat-0.1.0b1.dist-info/WHEEL
nonebot_plugin_qwen_chat-0.1.0b1.dist-info/top_level.txt
nonebot_plugin_qwen_chat-0.1.0b1.dist-info/RECORD
