Metadata-Version: 2.4
Name: nonebot_plugin_qwen_chat
Version: 0.1.0b1
Summary: 一个bot可以主动发送消息、表情包或自主让长消息分段发送的qwen大家族对话插件，让你的bot更拟人
Author-email: Ekac <udstudio.ekac@gmail.com>
License: GPL-3.0
Requires-Python: >=3.9
License-File: LICENSE
Requires-Dist: nonebot2
Requires-Dist: openai
Requires-Dist: httpx
Requires-Dist: os
Requires-Dist: nonebot-adapter-onebot
Requires-Dist: nonebot_plugin_alconna
Requires-Dist: json
Requires-Dist: typing
Dynamic: license-file
